beetools/__init__.py
beetools/msg.py
beetools/script.py
beetools/utils.py
beetools/venv.py
beetools-5.5.1.dist-info/METADATA
beetools-5.5.1.dist-info/WHEEL
beetools-5.5.1.dist-info/licenses/LICENSE.txt
beetools-5.5.1.dist-info/RECORD
