Metadata-Version: 2.4
Name: beetools
Version: 5.5.1
Summary: Tools for batch scripts, virtual environments and utilities.
License-Expression: MIT
License-File: LICENSE.txt
Author: Hendrik du Toit
Author-email: hendrik@brightedge.co.za
Maintainer: Hendrik du Toit
Maintainer-email: hendrikdt@citiqprepaid.co.za
Requires-Python: >=3.10
Classifier: Development Status :: 5 - Production/Stable
Classifier: Intended Audience :: Developers
Classifier: Topic :: Software Development
Classifier: Topic :: Software Development :: Version Control
Classifier: Topic :: Software Development :: Version Control :: Git
Classifier: License :: OSI Approved :: MIT License
Classifier: Programming Language :: Python :: 3.10
Classifier: Programming Language :: Python :: 3.11
Classifier: Programming Language :: Python :: 3.12
Classifier: Programming Language :: Python :: 3.13
Requires-Dist: termcolor (>=2.5.0,<3.0.0)
Project-URL: Homepage, https://github.com/BrightEdgeeServices/beetools
Project-URL: Repository, https://github.com/BrightEdgeeServices/beetools.git
Project-URL: changelog, https://github.com/BrightEdgeeServices/beetools/releases
Project-URL: issues, https://github.com/BrightEdgeeServices/beetools/issues
